{
  "as_of": "2026-05-31",
  "weight_used": 0.7,
  "games": [
    {
      "sb_id": 656678,
      "week": 10,
      "date": "2026-05-31",
      "home": "DC",
      "away": "ORL",
      "model": {
        "spread": -3.57,
        "total": 42.8,
        "home_score": 23.2,
        "away_score": 19.6,
        "home_wp": 0.6398,
        "components": {
          "elo_diff_inc_hfa": 81.9,
          "spread_elo": 2.48,
          "spread_eff": 4.65,
          "ppd_home": 2.31,
          "ppd_away": 1.86,
          "expected_drives_per_team": 10.25,
          "weather_mult": 1.0,
          "weather": ""
        }
      },
      "derived": {
        "h1_spread": -1.96,
        "h1_total": 19.69,
        "home_team_total": 23.18,
        "away_team_total": 19.61
      },
      "market": {
        "home_team": "DC Defenders",
        "away_team": "Orlando Storm",
        "commence_time": "2026-05-31T16:00:00Z",
        "markets": {
          "h2h": {
            "side_a_label": "DC Defenders",
            "side_b_label": "Orlando Storm",
            "consensus_prob_a": 0.4869958617038737,
            "consensus_prob_b": 0.5130041382961265,
            "n_books": 5,
            "books_used": [
              "draftkings",
              "fanduel",
              "hardrockbet",
              "betmgm",
              "williamhill_us"
            ],
            "consensus_point": null,
            "best_price_a": {
              "book": "fanduel",
              "odds": 100.0
            },
            "best_price_b": {
              "book": "hardrockbet",
              "odds": -110.0
            }
          },
          "spreads": {
            "side_a_label": "DC Defenders",
            "side_b_label": "Orlando Storm",
            "consensus_prob_a": 0.5048786656857325,
            "consensus_prob_b": 0.4951213343142677,
            "n_books": 5,
            "books_used": [
              "draftkings",
              "fanduel",
              "hardrockbet",
              "betmgm",
              "williamhill_us"
            ],
            "consensus_point": 1.4,
            "best_price_a": {
              "book": "fanduel",
              "odds": -105.0
            },
            "best_price_b": {
              "book": "draftkings",
              "odds": 100.0
            }
          },
          "totals": {
            "side_a_label": "Over",
            "side_b_label": "Under",
            "consensus_prob_a": 0.4962863497784033,
            "consensus_prob_b": 0.5037136502215968,
            "n_books": 5,
            "books_used": [
              "draftkings",
              "fanduel",
              "hardrockbet",
              "betmgm",
              "williamhill_us"
            ],
            "consensus_point": 46.5,
            "best_price_a": {
              "book": "draftkings",
              "odds": -105.0
            },
            "best_price_b": {
              "book": "williamhill_us",
              "odds": -108.0
            }
          }
        }
      },
      "bayes_weight": 0.7,
      "candidates": [
        {
          "label": "DC ML",
          "market": "moneyline",
          "side": "home_ml",
          "p_model": 0.594,
          "p_market": 0.487,
          "book": "fanduel",
          "american_odds": 100.0,
          "decimal_odds": 2.0,
          "edge_prob": 0.094,
          "edge_ev": 0.1879,
          "stake_pct": 0.02,
          "full_kelly_pct": 0.1879,
          "passes_threshold": true,
          "reason": ""
        },
        {
          "label": "ORL ML",
          "market": "moneyline",
          "side": "away_ml",
          "p_model": 0.406,
          "p_market": 0.513,
          "book": "hardrockbet",
          "american_odds": -110.0,
          "decimal_odds": 1.9091,
          "edge_prob": -0.1178,
          "edge_ev": -0.2248,
          "stake_pct": 0.0,
          "full_kelly_pct": -0.2473,
          "passes_threshold": false,
          "reason": ""
        },
        {
          "label": "DC +1.4",
          "market": "spread",
          "side": "home_spread",
          "p_model": 0.6241,
          "p_market": 0.5049,
          "book": "fanduel",
          "american_odds": -105.0,
          "decimal_odds": 1.9524,
          "edge_prob": 0.1119,
          "edge_ev": 0.2186,
          "stake_pct": 0.02,
          "full_kelly_pct": 0.2295,
          "passes_threshold": true,
          "reason": ""
        },
        {
          "label": "ORL -1.4",
          "market": "spread",
          "side": "away_spread",
          "p_model": 0.3759,
          "p_market": 0.4951,
          "book": "draftkings",
          "american_odds": 100.0,
          "decimal_odds": 2.0,
          "edge_prob": -0.1241,
          "edge_ev": -0.2483,
          "stake_pct": 0.0,
          "full_kelly_pct": -0.2483,
          "passes_threshold": false,
          "reason": ""
        },
        {
          "label": "Over 46.5",
          "market": "total",
          "side": "over",
          "p_model": 0.4291,
          "p_market": 0.4963,
          "book": "draftkings",
          "american_odds": -105.0,
          "decimal_odds": 1.9524,
          "edge_prob": -0.0831,
          "edge_ev": -0.1622,
          "stake_pct": 0.0,
          "full_kelly_pct": -0.1703,
          "passes_threshold": false,
          "reason": ""
        },
        {
          "label": "Under 46.5",
          "market": "total",
          "side": "under",
          "p_model": 0.5709,
          "p_market": 0.5037,
          "book": "williamhill_us",
          "american_odds": -108.0,
          "decimal_odds": 1.9259,
          "edge_prob": 0.0517,
          "edge_ev": 0.0995,
          "stake_pct": 0.02,
          "full_kelly_pct": 0.1074,
          "passes_threshold": true,
          "reason": ""
        }
      ]
    },
    {
      "sb_id": 656679,
      "week": 10,
      "date": "2026-05-31",
      "home": "CLB",
      "away": "LOU",
      "model": {
        "spread": 2.17,
        "total": 47.43,
        "home_score": 22.6,
        "away_score": 24.8,
        "home_wp": 0.4162,
        "components": {
          "elo_diff_inc_hfa": -35.3,
          "spread_elo": -1.07,
          "spread_eff": -3.27,
          "ppd_home": 2.15,
          "ppd_away": 2.47,
          "expected_drives_per_team": 10.25,
          "weather_mult": 1.0,
          "weather": ""
        }
      },
      "derived": {
        "h1_spread": 1.19,
        "h1_total": 21.82,
        "home_team_total": 22.63,
        "away_team_total": 24.8
      },
      "market": {
        "home_team": "Columbus Aviators",
        "away_team": "Louisville Kings",
        "commence_time": "2026-05-31T22:00:00Z",
        "markets": {
          "h2h": {
            "side_a_label": "Columbus Aviators",
            "side_b_label": "Louisville Kings",
            "consensus_prob_a": 0.4504584275164983,
            "consensus_prob_b": 0.5495415724835019,
            "n_books": 5,
            "books_used": [
              "draftkings",
              "fanduel",
              "hardrockbet",
              "betmgm",
              "williamhill_us"
            ],
            "consensus_point": null,
            "best_price_a": {
              "book": "fanduel",
              "odds": 120.0
            },
            "best_price_b": {
              "book": "draftkings",
              "odds": -125.0
            }
          },
          "spreads": {
            "side_a_label": "Columbus Aviators",
            "side_b_label": "Louisville Kings",
            "consensus_prob_a": 0.49883901196695585,
            "consensus_prob_b": 0.5011609880330443,
            "n_books": 5,
            "books_used": [
              "draftkings",
              "fanduel",
              "hardrockbet",
              "betmgm",
              "williamhill_us"
            ],
            "consensus_point": 1.5,
            "best_price_a": {
              "book": "draftkings",
              "odds": -108.0
            },
            "best_price_b": {
              "book": "fanduel",
              "odds": -110.0
            }
          },
          "totals": {
            "side_a_label": "Over",
            "side_b_label": "Under",
            "consensus_prob_a": 0.5046458092303763,
            "consensus_prob_b": 0.49535419076962384,
            "n_books": 5,
            "books_used": [
              "draftkings",
              "fanduel",
              "hardrockbet",
              "betmgm",
              "williamhill_us"
            ],
            "consensus_point": 46.3,
            "best_price_a": {
              "book": "fanduel",
              "odds": -110.0
            },
            "best_price_b": {
              "book": "draftkings",
              "odds": 100.0
            }
          }
        }
      },
      "bayes_weight": 0.7,
      "candidates": [
        {
          "label": "CLB ML",
          "market": "moneyline",
          "side": "home_ml",
          "p_model": 0.4265,
          "p_market": 0.4505,
          "book": "fanduel",
          "american_odds": 120.0,
          "decimal_odds": 2.2,
          "edge_prob": -0.0281,
          "edge_ev": -0.0617,
          "stake_pct": 0.0,
          "full_kelly_pct": -0.0515,
          "passes_threshold": false,
          "reason": ""
        },
        {
          "label": "LOU ML",
          "market": "moneyline",
          "side": "away_ml",
          "p_model": 0.5735,
          "p_market": 0.5495,
          "book": "draftkings",
          "american_odds": -125.0,
          "decimal_odds": 1.8,
          "edge_prob": 0.018,
          "edge_ev": 0.0323,
          "stake_pct": 0.0101,
          "full_kelly_pct": 0.0404,
          "passes_threshold": false,
          "reason": ""
        },
        {
          "label": "CLB +1.5",
          "market": "spread",
          "side": "home_spread",
          "p_model": 0.483,
          "p_market": 0.4988,
          "book": "draftkings",
          "american_odds": -108.0,
          "decimal_odds": 1.9259,
          "edge_prob": -0.0363,
          "edge_ev": -0.0699,
          "stake_pct": 0.0,
          "full_kelly_pct": -0.0754,
          "passes_threshold": false,
          "reason": ""
        },
        {
          "label": "LOU -1.5",
          "market": "spread",
          "side": "away_spread",
          "p_model": 0.517,
          "p_market": 0.5012,
          "book": "fanduel",
          "american_odds": -110.0,
          "decimal_odds": 1.9091,
          "edge_prob": -0.0068,
          "edge_ev": -0.0129,
          "stake_pct": 0.0,
          "full_kelly_pct": -0.0142,
          "passes_threshold": false,
          "reason": ""
        },
        {
          "label": "Over 46.3",
          "market": "total",
          "side": "over",
          "p_model": 0.5217,
          "p_market": 0.5046,
          "book": "fanduel",
          "american_odds": -110.0,
          "decimal_odds": 1.9091,
          "edge_prob": -0.0021,
          "edge_ev": -0.004,
          "stake_pct": 0.0,
          "full_kelly_pct": -0.0044,
          "passes_threshold": false,
          "reason": ""
        },
        {
          "label": "Under 46.3",
          "market": "total",
          "side": "under",
          "p_model": 0.4783,
          "p_market": 0.4954,
          "book": "draftkings",
          "american_odds": 100.0,
          "decimal_odds": 2.0,
          "edge_prob": -0.0217,
          "edge_ev": -0.0434,
          "stake_pct": 0.0,
          "full_kelly_pct": -0.0434,
          "passes_threshold": false,
          "reason": ""
        }
      ]
    }
  ],
  "n_candidates_passing": 3,
  "n_total_candidates": 12
}